LICENSE
MANIFEST.in
README.md
setup.py
objopt/__init__.py
objopt/losses.py
objopt/optimizers.py
objopt/test_losses.py
objopt.egg-info/PKG-INFO
objopt.egg-info/SOURCES.txt
objopt.egg-info/dependency_links.txt
objopt.egg-info/not-zip-safe
objopt.egg-info/requires.txt
objopt.egg-info/top_level.txt