Metadata-Version: 1.2
Name: objopt
Version: 0.2.0
Summary: Object oriented optimization
Home-page: https://github.com/stsievert/objopt
Author: Scott Sievert
Author-email: dev@stsievert.com
License: MIT
Keywords: optimization,machine learning,theory,object oriented
Platform: UNKNOWN
Classifier: Programming Language :: Python
Classifier: Topic :: Scientific/Engineering :: Mathematics
Classifier: Development Status :: 2 - Pre-Alpha
Classifier: Intended Audience :: Science/Research
Requires-Python: >=2.7, !=3.0.*, !=3.1.*, !=3.2.*, !=3.3.*
